{
  "fill" : {
    "automatic-gradient" : "display-p3:0.96365,1.00000,0.96669,1.00000"
  },
  "groups" : [
    {
      "layers" : [
        {
          "blend-mode" : "normal",
          "fill" : {
            "solid" : "display-p3:1.00000,0.06975,0.00000,1.00000"
          },
          "image-name" : "graduate-hat.png",
          "name" : "graduate-hat",
          "position" : {
            "scale" : 2,
            "translation-in-points" : [
              0,
              0
            ]
          }
        }
      ],
      "shadow" : {
        "kind" : "neutral",
        "opacity" : 0.5
      },
      "translucency" : {
        "enabled" : true,
        "value" : 0.5
      }
    }
  ],
  "supported-platforms" : {
    "squares" : "shared"
  }
}